flybywire/__init__.py
flybywire/core.py
flybywire/dom.py
flybywire/misc.py
flybywire/ui.py
flybywire/static/flybywire.js
flybywire/static/main.html
flybywire-0.0.2.dist-info/DESCRIPTION.rst
flybywire-0.0.2.dist-info/METADATA
flybywire-0.0.2.dist-info/RECORD
flybywire-0.0.2.dist-info/WHEEL
flybywire-0.0.2.dist-info/metadata.json
flybywire-0.0.2.dist-info/pbr.json
flybywire-0.0.2.dist-info/top_level.txt
