Metadata-Version: 2.0
Name: flybywire
Version: 0.0.2
Summary: A declarative library for building virtual-DOM user interfaces in pure Python.
Home-page: https://github.com/thomasantony/flybywire
Author: Thomas Antony
Author-email: tantony.purdue@gmail.com
License: MIT
Keywords: react
